stoepsel/__init__.py
stoepsel/logger.py
stoepsel/stoepsel.py
stoepsel-0.3.7.dist-info/licenses/LICENSE
tests/__init__.py
tests/tests.py
tests/cyclic_plugins/plug1.py
tests/cyclic_plugins/plug2.py
tests/cyclic_plugins/plug3.py
tests/simple_plugins/plug1.py
tests/threaded_plugin/plug1.py
tests/unmatched_plugins/plug2.py
tests/unmatched_plugins/plug3.py
tests/unresolved_plugins/plug1.py
stoepsel-0.3.7.dist-info/METADATA
stoepsel-0.3.7.dist-info/WHEEL
stoepsel-0.3.7.dist-info/top_level.txt
stoepsel-0.3.7.dist-info/RECORD
