Metadata-Version: 2.4
Name: stoepsel
Version: 0.3.7
Summary: a simple but powerful plugin mechanism for python
Home-page: https://gitlab.com/rapp.jens/stoepsel
Author: TecDroiD
Author-email: TecDroiD <rapp.jens@gmail.com>
License-Expression: GPL-3.0
Classifier: Programming Language :: Python :: 3
Classifier: Operating System :: OS Independent
Requires-Python: >=3.8
License-File: LICENSE
Requires-Dist: build
Dynamic: license-file
